Metadata-Version: 1.0
Name: distrib-pkg
Version: 0.1
Summary: Gaussian and Binomial distributions
Home-page: UNKNOWN
Author: Nati Aluk
Author-email: UNKNOWN
License: UNKNOWN
Platform: UNKNOWN
